AUTHORS
COPYING
MANIFEST.in
Makefile.in
README
bower.json
configure.ac
install-sh
lazycelery.sh
lazyserver.sh
lazystarter.sh
mediagoblin.example.ini
paste.ini
runtests.sh
setup.py
devtools/compile_translations.sh
devtools/make_example_database.sh
devtools/maketarball.sh
devtools/pootle-exclude.txt
devtools/update_extlib.sh
devtools/update_translations.sh
docs/source/index.rst
docs/source/api/activities.rst
docs/source/api/authentication.rst
docs/source/api/objects.rst
docs/source/devel/codebase.rst
docs/source/devel/migrations.rst
docs/source/devel/originaldesigndecisions.rst
docs/source/devel/storage.rst
docs/source/plugindocs/basic_auth.rst
docs/source/plugindocs/flatpagesfile.rst
docs/source/plugindocs/ldap.rst
docs/source/plugindocs/openid.rst
docs/source/plugindocs/persona.rst
docs/source/plugindocs/raven.rst
docs/source/plugindocs/sampleplugin.rst
docs/source/plugindocs/trim_whitespace.rst
docs/source/pluginwriter/api.rst
docs/source/pluginwriter/authhooks.rst
docs/source/pluginwriter/database.rst
docs/source/pluginwriter/foreward.rst
docs/source/pluginwriter/hooks.rst
docs/source/pluginwriter/media_type_hooks.rst
docs/source/pluginwriter/quickstart.rst
docs/source/pluginwriter/tests.rst
docs/source/siteadmin/about.rst
docs/source/siteadmin/commandline-upload.rst
docs/source/siteadmin/configuration.rst
docs/source/siteadmin/deploying.rst
docs/source/siteadmin/foreword.rst
docs/source/siteadmin/help.rst
docs/source/siteadmin/media-types.rst
docs/source/siteadmin/plugins.rst
docs/source/siteadmin/production-deployments.rst
docs/source/siteadmin/relnotes.rst
docs/source/siteadmin/theming.rst
docs/source/themes/mg/layout.html
extlib/README
extlib/flask-wtf/LICENSE
extlib/flask-wtf/html5.py
extlib/freesound/audioprocessing.py
extlib/inconsolata/INFO.txt
extlib/inconsolata/Inconsolata.otf
extlib/inconsolata/Inconsolata.pfa
extlib/inconsolata/Inconsolata.sfd
extlib/inconsolata/OFL_1.1.txt
extlib/inconsolata/textest.pdf
extlib/lato/Lato-Bold.ttf
mediagoblin.egg-info/PKG-INFO
mediagoblin.egg-info/SOURCES.txt
mediagoblin.egg-info/dependency_links.txt
mediagoblin.egg-info/entry_points.txt
mediagoblin.egg-info/not-zip-safe
mediagoblin.egg-info/requires.txt
mediagoblin.egg-info/top_level.txt
